traceai_mistralai/__init__.py
traceai_mistralai/_chat_wrapper.py
traceai_mistralai/_request_attributes_extractor.py
traceai_mistralai/_response_accumulator.py
traceai_mistralai/_response_attributes_extractor.py
traceai_mistralai/_stream.py
traceai_mistralai/_utils.py
traceai_mistralai/_with_span.py
traceai_mistralai/package.py
traceai_mistralai/py.typed
traceai_mistralai/version.py
traceai_mistralai-0.1.7.dist-info/METADATA
traceai_mistralai-0.1.7.dist-info/WHEEL
traceai_mistralai-0.1.7.dist-info/RECORD
